odoo8_addon_project_task_materials_stock-8.0.1.0.0.99.dev44-py3.8-nspkg.pth
odoo_addons/project_task_materials_stock/README.rst
odoo_addons/project_task_materials_stock/__init__.py
odoo_addons/project_task_materials_stock/__openerp__.py
odoo_addons/project_task_materials_stock/data/project_task_materials_data.xml
odoo_addons/project_task_materials_stock/i18n/ar.po
odoo_addons/project_task_materials_stock/i18n/bg.po
odoo_addons/project_task_materials_stock/i18n/ca.po
odoo_addons/project_task_materials_stock/i18n/de.po
odoo_addons/project_task_materials_stock/i18n/el.po
odoo_addons/project_task_materials_stock/i18n/es.po
odoo_addons/project_task_materials_stock/i18n/es_AR.po
odoo_addons/project_task_materials_stock/i18n/es_CR.po
odoo_addons/project_task_materials_stock/i18n/es_MX.po
odoo_addons/project_task_materials_stock/i18n/es_VE.po
odoo_addons/project_task_materials_stock/i18n/fi.po
odoo_addons/project_task_materials_stock/i18n/fr.po
odoo_addons/project_task_materials_stock/i18n/gl.po
odoo_addons/project_task_materials_stock/i18n/hr.po
odoo_addons/project_task_materials_stock/i18n/hr_HR.po
odoo_addons/project_task_materials_stock/i18n/hu.po
odoo_addons/project_task_materials_stock/i18n/id.po
odoo_addons/project_task_materials_stock/i18n/it.po
odoo_addons/project_task_materials_stock/i18n/ja.po
odoo_addons/project_task_materials_stock/i18n/lt.po
odoo_addons/project_task_materials_stock/i18n/lv.po
odoo_addons/project_task_materials_stock/i18n/mk.po
odoo_addons/project_task_materials_stock/i18n/mn.po
odoo_addons/project_task_materials_stock/i18n/nb.po
odoo_addons/project_task_materials_stock/i18n/nl.po
odoo_addons/project_task_materials_stock/i18n/pl.po
odoo_addons/project_task_materials_stock/i18n/project_task_materials_stock.pot
odoo_addons/project_task_materials_stock/i18n/pt.po
odoo_addons/project_task_materials_stock/i18n/pt_BR.po
odoo_addons/project_task_materials_stock/i18n/pt_PT.po
odoo_addons/project_task_materials_stock/i18n/ro.po
odoo8_addon_project_task_materials_stock-8.0.1.0.0.99.dev44.dist-info/METADATA
odoo8_addon_project_task_materials_stock-8.0.1.0.0.99.dev44.dist-info/WHEEL
odoo8_addon_project_task_materials_stock-8.0.1.0.0.99.dev44.dist-info/namespace_packages.txt
odoo8_addon_project_task_materials_stock-8.0.1.0.0.99.dev44.dist-info/top_level.txt
odoo8_addon_project_task_materials_stock-8.0.1.0.0.99.dev44.dist-info/RECORD
